lbdc/__init__.py
lbdc/__main__.py
lbdc-0.0.3.dist-info/LICENSE
lbdc-0.0.3.dist-info/METADATA
lbdc-0.0.3.dist-info/WHEEL
lbdc-0.0.3.dist-info/top_level.txt
lbdc-0.0.3.dist-info/RECORD
